MANIFEST.in
requirements.txt
setup.py
tornado_cors/__init__.py
tornado_cors/custom_decorator.py
tornado_cors.egg-info/PKG-INFO
tornado_cors.egg-info/SOURCES.txt
tornado_cors.egg-info/dependency_links.txt
tornado_cors.egg-info/requires.txt
tornado_cors.egg-info/top_level.txt