Metadata-Version: 1.1
Name: tornado-cors
Version: 0.6.0
Summary: CORS support for Tornado
Home-page: https://github.com/globocom/tornado-cors
Author: globo.com
Author-email: guilherme.cirne@corp.globo.com
License: MIT
Keywords: tornado cors
Platform: UNKNOWN
Classifier: Development Status :: 4 - Beta
Classifier: Intended Audience :: Developers
Classifier: License :: OSI Approved :: MIT License
Classifier: Natural Language :: English
Classifier: Operating System :: MacOS
Classifier: Operating System :: POSIX :: Linux
Classifier: Programming Language :: Python :: 2.7
Classifier: Programming Language :: Python :: 3.2
Classifier: Programming Language :: Python :: 3.3
Classifier: Topic :: Software Development :: Libraries
